gearshift/__init__.py
gearshift/_version.py
gearshift/cli/__init__.py
gearshift/core/__init__.py
gearshift/core/load/__init__.py
gearshift/core/load/excel.py
gearshift/core/load/excel_dice.py
gearshift/core/load/speed_phases/phase.ftr
gearshift/core/load/speed_phases/scale.ftr
gearshift/core/load/speed_phases/trace.ftr
gearshift/core/model/__init__.py
gearshift/core/model/calculateShiftpointsNdvFullPC/__init__.py
gearshift/core/model/calculateShiftpointsNdvFullPC/corrections/__init__.py
gearshift/core/model/scaleTrace/__init__.py
gearshift/core/write/__init__.py
gearshift/core/write/excel.py
gearshift/demos/gs_input_demo.xlsx
gearshift/demos/gs_input_demo_empty.xlsx
wltp_jrshift-2.0.3.dist-info/LICENSE
wltp_jrshift-2.0.3.dist-info/METADATA
wltp_jrshift-2.0.3.dist-info/WHEEL
wltp_jrshift-2.0.3.dist-info/entry_points.txt
wltp_jrshift-2.0.3.dist-info/top_level.txt
wltp_jrshift-2.0.3.dist-info/zip-safe
wltp_jrshift-2.0.3.dist-info/RECORD
