Metadata-Version: 2.1
Name: wltp-jrshift
Version: 2.0.3
Summary: Gearshift tool implement the Sub-Annex 1 and Sub-Annex 2 of theCOMMISSION REGULATION (EU) 2017/1151 of 1 June 2017 - Annex XXI
Author: GEARSHIFT-Team
Author-email: jrc-ldvs-co2@ec.europa.eu
License: EUPL 1.1+
Keywords: GEARSHIFT,WLTP,vehicle,automotive,EU,JRC,IET,policy,monitoring,simulator
Platform: any
Classifier: Programming Language :: Python
Classifier: Programming Language :: Python :: 3
Classifier: Programming Language :: Python :: 3.6
Classifier: Programming Language :: Python :: 3.7
Classifier: Programming Language :: Python :: Implementation :: CPython
Classifier: Development Status :: 4 - Beta
Classifier: Natural Language :: English
Classifier: Intended Audience :: Developers
Classifier: Intended Audience :: Science/Research
Classifier: Intended Audience :: Manufacturing
Classifier: Environment :: Console
Classifier: License :: OSI Approved :: European Union Public Licence 1.1 (EUPL 1.1)
Classifier: Natural Language :: English
Classifier: Operating System :: MacOS :: MacOS X
Classifier: Operating System :: Microsoft :: Windows
Classifier: Operating System :: POSIX
Classifier: Operating System :: Unix
Classifier: Operating System :: OS Independent
Classifier: Topic :: Scientific/Engineering
Classifier: Topic :: Scientific/Engineering :: Information Analysis
Requires-Python: >=3.5
License-File: LICENSE
Requires-Dist: PyYAML
Requires-Dist: click
Requires-Dist: pandas
Requires-Dist: schedula[all] (>=1.1.1)
Requires-Dist: click-log
Requires-Dist: tqdm
Requires-Dist: regex
Requires-Dist: numpy (!=1.19.3)
Requires-Dist: scipy
Requires-Dist: pyarrow
Requires-Dist: XlsxWriter
Requires-Dist: ruamel.yaml
Requires-Dist: openpyxl
Requires-Dist: xlrd
Provides-Extra: all
Requires-Dist: graphviz ; extra == 'all'
Requires-Dist: Pygments ; extra == 'all'
Requires-Dist: regex ; extra == 'all'
Requires-Dist: docutils ; extra == 'all'
Requires-Dist: lxml ; extra == 'all'
Requires-Dist: xlrd ; extra == 'all'
Requires-Dist: click ; extra == 'all'
Requires-Dist: jinja2 ; extra == 'all'
Requires-Dist: click-log ; extra == 'all'
Requires-Dist: asteval ; extra == 'all'
Requires-Dist: ruamel.yaml (>=0.16.5) ; extra == 'all'
Requires-Dist: pandas (>=0.21.0) ; extra == 'all'
Requires-Dist: syncing (>=1.0.4) ; extra == 'all'
Requires-Dist: beautifulsoup4 ; extra == 'all'
Requires-Dist: dill ; extra == 'all'
Requires-Dist: flask ; extra == 'all'
Requires-Dist: pandalone[xlrd] (<0.3) ; extra == 'all'
Requires-Dist: plotly ; extra == 'all'
Provides-Extra: cli
Requires-Dist: click ; extra == 'cli'
Requires-Dist: click-log ; extra == 'cli'
Provides-Extra: dev
Requires-Dist: graphviz ; extra == 'dev'
Requires-Dist: Pygments ; extra == 'dev'
Requires-Dist: regex ; extra == 'dev'
Requires-Dist: docutils ; extra == 'dev'
Requires-Dist: lxml ; extra == 'dev'
Requires-Dist: xlrd ; extra == 'dev'
Requires-Dist: click ; extra == 'dev'
Requires-Dist: jinja2 ; extra == 'dev'
Requires-Dist: click-log ; extra == 'dev'
Requires-Dist: asteval ; extra == 'dev'
Requires-Dist: ruamel.yaml (>=0.16.5) ; extra == 'dev'
Requires-Dist: pandas (>=0.21.0) ; extra == 'dev'
Requires-Dist: syncing (>=1.0.4) ; extra == 'dev'
Requires-Dist: beautifulsoup4 ; extra == 'dev'
Requires-Dist: dill ; extra == 'dev'
Requires-Dist: flask ; extra == 'dev'
Requires-Dist: pandalone[xlrd] (<0.3) ; extra == 'dev'
Requires-Dist: plotly ; extra == 'dev'
Requires-Dist: wheel ; extra == 'dev'
Requires-Dist: sphinx ; extra == 'dev'
Requires-Dist: gitchangelog ; extra == 'dev'
Requires-Dist: mako ; extra == 'dev'
Requires-Dist: sphinx-rtd-theme ; extra == 'dev'
Requires-Dist: setuptools (>=36.0.1) ; extra == 'dev'
Requires-Dist: sphinxcontrib-restbuilder ; extra == 'dev'
Requires-Dist: nose ; extra == 'dev'
Requires-Dist: coveralls ; extra == 'dev'
Requires-Dist: ddt ; extra == 'dev'
Requires-Dist: sphinx-click ; extra == 'dev'
Provides-Extra: io
Requires-Dist: pandas (>=0.21.0) ; extra == 'io'
Requires-Dist: dill ; extra == 'io'
Requires-Dist: regex ; extra == 'io'
Requires-Dist: pandalone[xlrd] (<0.3) ; extra == 'io'
Requires-Dist: xlrd ; extra == 'io'
Requires-Dist: asteval ; extra == 'io'
Requires-Dist: ruamel.yaml (>=0.16.5) ; extra == 'io'
Provides-Extra: plot
Requires-Dist: flask ; extra == 'plot'
Requires-Dist: regex ; extra == 'plot'
Requires-Dist: graphviz ; extra == 'plot'
Requires-Dist: Pygments ; extra == 'plot'
Requires-Dist: lxml ; extra == 'plot'
Requires-Dist: beautifulsoup4 ; extra == 'plot'
Requires-Dist: jinja2 ; extra == 'plot'
Requires-Dist: docutils ; extra == 'plot'
Requires-Dist: plotly ; extra == 'plot'
Provides-Extra: sync
Requires-Dist: syncing (>=1.0.4) ; extra == 'sync'
Requires-Dist: pandas (>=0.21.0) ; extra == 'sync'
Requires-Dist: ruamel.yaml (>=0.16.5) ; extra == 'sync'
